{"purchase":{"id":4259773,"contracts":[{"id":1950527,"contractInfos":[{"id":2313010,"contractInfoType":null,"contractSubject":null,"name":null,"publishDate":null,"status":null,"version":null}],"regNum":"57719167509160000340001","tmstmp":null}],"customerId":1709},"purchaseMethod":{"id":8190,"changeable":true,"competitive":false,"digitalPurchase":true,"extended":false,"hasPhases":true,"hasPurchases":"P","methodType":"IS","name":"Открытый конкурс","status":"RELEVANT","typal":false,"typalKind":null},"timeZones":[{"actual":true,"ahead":false,"id":12,"name":"МСК-1 (СГВ+2) Калининград","offset":-1,"shortName":"МСК-1"},{"actual":true,"ahead":false,"id":13,"name":"МСК (СГВ+3) Москва, Волгоград","offset":0,"shortName":"МСК"},{"actual":true,"ahead":true,"id":14,"name":"МСК+1 (СГВ+4) Самара","offset":1,"shortName":"МСК+1"},{"actual":true,"ahead":true,"id":15,"name":"МСК+2 (СГВ+5) Екатеринбург, Челябинск, Уфа","offset":2,"shortName":"МСК+2"},{"actual":true,"ahead":true,"id":16,"name":"МСК+3 (СГВ+6) Новосибирск, Омск","offset":3,"shortName":"МСК+3"},{"actual":true,"ahead":true,"id":17,"name":"МСК+4 (СГВ+7) Красноярск","offset":4,"shortName":"МСК+4"},{"actual":true,"ahead":true,"id":18,"name":"МСК+5 (СГВ+8) Иркутск","offset":5,"shortName":"МСК+5"},{"actual":true,"ahead":true,"id":19,"name":"МСК+6 (СГВ+9) Якутск","offset":6,"shortName":"МСК+6"},{"actual":true,"ahead":true,"id":20,"name":"МСК+7 (СГВ+10) Владивосток, Хабаровск","offset":7,"shortName":"МСК+7"},{"actual":true,"ahead":true,"id":21,"name":"МСК+8 (СГВ+11) Среднеколымск","offset":8,"shortName":"МСК+8"},{"actual":true,"ahead":true,"id":22,"name":"МСК+9 (СГВ+12) Петропавловск-Камчатский","offset":9,"shortName":"МСК+9"}],"noticeInfo":{"id":4973156,"additionalContactInfo":null,"additionalPricesMatchingDate":null,"applExaminationTime":1476792000000,"applSubmisionPlace":null,"applSubmisionStartDate":null,"applSubmissionCloseTime":1476691200000,"auctionTime":null,"considerationSecondPartDate":null,"contractorAgencyType":0,"customerFullAddress":"105318, г МОСКВА, ул ТКАЦКАЯ, дом ДОМ 1","customerInn":"7719167509","customerKpp":"771901001","customerName":"АКЦИОНЕРНОЕ ОБЩЕСТВО \"ПРОЕКТНО-ИЗЫСКАТЕЛЬСКИЙ И НАУЧНО-ИССЛЕДОВАТЕЛЬСКИЙ ИНСТИТУТ ПО ПРОЕКТИРОВАНИЮ ЭНЕРГЕТИЧЕСКИХ СИСТЕМ И ЭЛЕКТРИЧЕСКИХ СЕТЕЙ \"ЭНЕРГОСЕТЬПРОЕКТ\"","customerOgrn":"1027700386922","customerPostalAddress":"105058, Москва, Ткацкая, дом 1","docProvisionPlace":"ЭТП группы B2B-Center","email":"Terehova_T@oaoesp.ru","envelopeOpeningTime":null,"fax":null,"firstName":"Татьяна","lastName":"Терехова ","patronymic":"Петровна","phone":"+7 (495) 6529269","purchaseName":"Право заключения договора на оказание услуг по охране объектов. (50489)","quotationExaminationTime":null,"summingupTime":null,"timezoneId":13,"urlVsrz":"http://www.b2b-energo.ru/market/view_tender.html?id=50489","lots":[{"centralized":false,"commoditiesWorkServiceses":[{"id":9841767,"additionalInfo":null,"amountOfCommodities":null,"deliveryPlace":null,"impossibleToDetermineAttr":true,"okei":null,"okpd2":{"code":"80.1","id":8874201,"name":"Услуги частных охранных служб"},"okved2":{"code":"80.10","id":8831520,"name":"Деятельность частных охранных служб","section":"N"},"orderNumber":1}],"commodityPrice":null,"commodityPriceRub":null,"contractSubject":"Оказание услуг по охране объектов.","currency":{"id":1,"actual":true,"code":"RUB","dateutv":null,"digitalCode":"643","endtActiveDate":1303489510000,"lastModifyDate":1365422030000,"name":"Российский рубль","shortName":"Россия","startActiveDate":1303489510000},"deliveryPlace":{"regionId":null,"address":"105318, Россия, г. Москва, ул. Ткацкая, д.1"},"deliveryPlaceIndication":"GL","exchangeRate":null,"exchangeRateDate":null,"id":5783469,"impossibleToDeterminePrice":false,"inputTypeNMSK":null,"jointLot":false,"ordinalNumber":1,"planId":230849,"planInfoId":1267633,"planPositionId":138207359,"planType":"COMMODITY","priceInformation":null,"reestrNumber":"2150138490","startingContractPrice":3600000,"startingContractPriceRub":null,"lotApplications":[{"id":6582861,"additionalPriceCurrency":null,"allocated":false,"applications":[{"id":10842326,"additionalIdentificationNumber":null,"additionalPrice":null,"address":"396072, Россия, Воронежская область,  г. Нововоронеж, ул. Космонавтов, д.10 а оф.2","allowance":"NOT_INDICATED","allowanceQualyfingCompetition":null,"appCommodityDeliveryPlace":null,"applicationDate":1476686318000,"applicationDateOnly":null,"applicationHours":null,"applicationMinutes":null,"applicationNumber":"1","assessmentResult":null,"calculatedPlace":null,"calculatedRating":null,"commissionDecisionPlace":null,"commodityAmount":null,"conditionProposals":null,"contactSigned":null,"contractExecutionTerm":null,"country":null,"countryId":null,"currency":1,"customerExplanationRequestReason":null,"customerName":"ООО ЧОП «Охранное агентство «Эскарп-НВ 1»","explanationRequestResult":null,"functionalCharacteristicsFinalOffer":null,"identificationNumber":null,"impossibleToDeterminePrice":false,"inn":"3651008453","kpp":"365101001","lastButOnePrice":null,"lastPrice":null,"notRFResident":false,"notRFResidentInfo":null,"ogrn":"1093668014307","physical":false,"place":"NOT_INDICATED","price":3316838.4,"priceInfo":null,"protocolFields":[],"protocolFieldsForAllowance":[],"protocolFieldsForPlace":[],"rating":null,"rejectionReason":null,"rejectionReasonCode":null,"rejectionReasonCodeQualyfingCompetition":null,"rejectionReasonQualyfingCompetition":null,"appLotCriterias":[],"customerExplanationRequests":[],"requirements":[],"provider":false,"notDishonest":true}],"assessmentInformation":null,"assessmentOrder":null,"currency":null,"documentRequirements":[],"lotApplicationsCriteria":null,"nonPrice":false,"offerInfo":null},{"id":6586404,"additionalPriceCurrency":null,"allocated":false,"applications":[{"id":10848200,"additionalIdentificationNumber":null,"additionalPrice":null,"address":"396072, Россия, Воронежская область,  г. Нововоронеж, ул. Космонавтов, д.10 а оф.2","allowance":"ALLOWED","allowanceQualyfingCompetition":null,"appCommodityDeliveryPlace":null,"applicationDate":1476686318000,"applicationDateOnly":null,"applicationHours":null,"applicationMinutes":null,"applicationNumber":"1","assessmentResult":null,"calculatedPlace":null,"calculatedRating":null,"commissionDecisionPlace":null,"commodityAmount":null,"conditionProposals":null,"contactSigned":null,"contractExecutionTerm":null,"country":null,"countryId":null,"currency":1,"customerExplanationRequestReason":null,"customerName":"ООО ЧОП «Охранное агентство «Эскарп-НВ 1»","explanationRequestResult":null,"functionalCharacteristicsFinalOffer":null,"identificationNumber":null,"impossibleToDeterminePrice":false,"inn":"3651008453","kpp":"365101001","lastButOnePrice":null,"lastPrice":null,"notRFResident":false,"notRFResidentInfo":null,"ogrn":"1093668014307","physical":false,"place":"NOT_INDICATED","price":3316838.4,"priceInfo":null,"protocolFields":[],"protocolFieldsForAllowance":[],"protocolFieldsForPlace":[],"rating":null,"rejectionReason":null,"rejectionReasonCode":null,"rejectionReasonCodeQualyfingCompetition":null,"rejectionReasonQualyfingCompetition":null,"appLotCriterias":[],"customerExplanationRequests":[],"requirements":[],"provider":false,"notDishonest":true}],"assessmentInformation":null,"assessmentOrder":null,"currency":null,"documentRequirements":[],"lotApplicationsCriteria":null,"nonPrice":false,"offerInfo":null},{"id":6586534,"additionalPriceCurrency":null,"allocated":false,"applications":[{"id":10848393,"additionalIdentificationNumber":null,"additionalPrice":null,"address":"396072, Россия, Воронежская область,  г. Нововоронеж, ул. Космонавтов, д.10 а оф.2","allowance":"NOT_INDICATED","allowanceQualyfingCompetition":null,"appCommodityDeliveryPlace":null,"applicationDate":1476686318000,"applicationDateOnly":null,"applicationHours":null,"applicationMinutes":null,"applicationNumber":"1","assessmentResult":null,"calculatedPlace":null,"calculatedRating":null,"commissionDecisionPlace":null,"commodityAmount":null,"conditionProposals":null,"contactSigned":null,"contractExecutionTerm":null,"country":null,"countryId":null,"currency":1,"customerExplanationRequestReason":null,"customerName":"ООО ЧОП «Охранное агентство «Эскарп-НВ 1»","explanationRequestResult":null,"functionalCharacteristicsFinalOffer":null,"identificationNumber":null,"impossibleToDeterminePrice":false,"inn":"3651008453","kpp":"365101001","lastButOnePrice":null,"lastPrice":null,"notRFResident":false,"notRFResidentInfo":null,"ogrn":"1093668014307","physical":false,"place":"FIRST_PLACE","price":3316838.4,"priceInfo":null,"protocolFields":[],"protocolFieldsForAllowance":[],"protocolFieldsForPlace":[],"rating":null,"rejectionReason":null,"rejectionReasonCode":null,"rejectionReasonCodeQualyfingCompetition":null,"rejectionReasonQualyfingCompetition":null,"appLotCriterias":[],"customerExplanationRequests":[],"requirements":[],"provider":false,"notDishonest":true}],"assessmentInformation":null,"assessmentOrder":null,"currency":null,"documentRequirements":[],"lotApplicationsCriteria":null,"nonPrice":false,"offerInfo":null}],"lotCriterias":null,"lotCustomers":[],"lotToLotCancellations":[],"lotToProtocolAllocations":[]}]}}